headnode_notifier.py
headnode_notifier-1.5.4.data/scripts/headnode_notifier.py
headnode_notifier-1.5.4.dist-info/METADATA
headnode_notifier-1.5.4.dist-info/RECORD
headnode_notifier-1.5.4.dist-info/WHEEL
headnode_notifier-1.5.4.dist-info/top_level.txt
